{
	"backtrace" : 4,
	"backtraceGraph" : 
	{
		"commands" : 
		[
			"add_custom_target",
			"qt_internal_show_extra_ide_sources",
			"qt_build_repo_end",
			"qt_build_repo"
		],
		"files" : 
		[
			"qtbase/cmake/QtBuildRepoHelpers.cmake",
			"qtremoteobjects/CMakeLists.txt"
		],
		"nodes" : 
		[
			{
				"file" : 1
			},
			{
				"command" : 3,
				"file" : 1,
				"line" : 22,
				"parent" : 0
			},
			{
				"command" : 2,
				"file" : 0,
				"line" : 503,
				"parent" : 1
			},
			{
				"command" : 1,
				"file" : 0,
				"line" : 353,
				"parent" : 2
			},
			{
				"command" : 0,
				"file" : 0,
				"line" : 438,
				"parent" : 3
			}
		]
	},
	"id" : "qtremoteobjects_licenses::@e3dd6c18c9e5ae4406ae",
	"name" : "qtremoteobjects_licenses",
	"paths" : 
	{
		"build" : "qtremoteobjects",
		"source" : "qtremoteobjects"
	},
	"sourceGroups" : 
	[
		{
			"name" : "",
			"sourceIndexes" : 
			[
				0,
				1,
				2,
				3,
				4,
				5,
				6
			]
		}
	],
	"sources" : 
	[
		{
			"backtrace" : 4,
			"path" : "qtremoteobjects/LICENSES/BSD-3-Clause.txt",
			"sourceGroupIndex" : 0
		},
		{
			"backtrace" : 4,
			"path" : "qtremoteobjects/LICENSES/GFDL-1.3-no-invariants-only.txt",
			"sourceGroupIndex" : 0
		},
		{
			"backtrace" : 4,
			"path" : "qtremoteobjects/LICENSES/GPL-2.0-only.txt",
			"sourceGroupIndex" : 0
		},
		{
			"backtrace" : 4,
			"path" : "qtremoteobjects/LICENSES/GPL-3.0-only.txt",
			"sourceGroupIndex" : 0
		},
		{
			"backtrace" : 4,
			"path" : "qtremoteobjects/LICENSES/LGPL-3.0-only.txt",
			"sourceGroupIndex" : 0
		},
		{
			"backtrace" : 4,
			"path" : "qtremoteobjects/LICENSES/LicenseRef-Qt-Commercial.txt",
			"sourceGroupIndex" : 0
		},
		{
			"backtrace" : 4,
			"path" : "qtremoteobjects/LICENSES/Qt-GPL-exception-1.0.txt",
			"sourceGroupIndex" : 0
		}
	],
	"type" : "UTILITY"
}
