{
	"backtrace" : 4,
	"backtraceGraph" : 
	{
		"commands" : 
		[
			"add_custom_target",
			"qt_internal_show_extra_ide_sources",
			"qt_build_repo_end",
			"qt_build_repo",
			"target_sources"
		],
		"files" : 
		[
			"qtbase/cmake/QtBuildRepoHelpers.cmake",
			"qt3d/CMakeLists.txt"
		],
		"nodes" : 
		[
			{
				"file" : 1
			},
			{
				"command" : 3,
				"file" : 1,
				"line" : 42,
				"parent" : 0
			},
			{
				"command" : 2,
				"file" : 0,
				"line" : 503,
				"parent" : 1
			},
			{
				"command" : 1,
				"file" : 0,
				"line" : 353,
				"parent" : 2
			},
			{
				"command" : 0,
				"file" : 0,
				"line" : 451,
				"parent" : 3
			},
			{
				"command" : 4,
				"file" : 0,
				"line" : 475,
				"parent" : 3
			}
		]
	},
	"id" : "qt3d_extra_files::@cd0eab48c1a3d16c536b",
	"name" : "qt3d_extra_files",
	"paths" : 
	{
		"build" : "qt3d",
		"source" : "qt3d"
	},
	"sourceGroups" : 
	[
		{
			"name" : "",
			"sourceIndexes" : 
			[
				0,
				1
			]
		}
	],
	"sources" : 
	[
		{
			"backtrace" : 5,
			"path" : "qt3d/.tag",
			"sourceGroupIndex" : 0
		},
		{
			"backtrace" : 5,
			"path" : "qt3d/config_help.txt",
			"sourceGroupIndex" : 0
		}
	],
	"type" : "UTILITY"
}
